README.rst
setup.cfg
setup.py
pyjapc/__init__.py
pyjapc/pyjapc.py
pyjapc/pyjapc.pyi
pyjapc/rbac_dialog.py
pyjapc/rbac_dialog.pyi
pyjapc/visualise_device.py
pyjapc.egg-info/PKG-INFO
pyjapc.egg-info/SOURCES.txt
pyjapc.egg-info/dependency_links.txt
pyjapc.egg-info/requires.txt
pyjapc.egg-info/top_level.txt