Metadata-Version: 2.1
Name: pyjapc
Version: 2.0.6
Summary: Python to FESA/LSA/INCA interface via JAPC
Home-page: https://gitlab.cern.ch/scripting-tools/pyjapc
Author: CERN MD Scripting Tools Community
Author-email: MD-scripting-tools@cern.ch
License: MIT
Platform: UNKNOWN
Provides-Extra: testing
Provides-Extra: doc
